search_tool/__init__.py
search_tool/cli.py
search_tool/config.py
search_tool/engines/__init__.py
search_tool/engines/base_engine.py
search_tool/engines/brave.py
search_tool/engines/duckduckgo.py
search_tool/engines/google.py
search_tool/exceptions.py
search_tool/models.py
search_tool/parsers/__init__.py
search_tool/parsers/base_parser.py
search_tool/parsers/brave.py
search_tool/parsers/duckduckgo.py
search_tool/parsers/google.py
search_tool/playwright_manager.py
search_tool/search.py
search_tool-0.1.1.dist-info/LICENSE
search_tool-0.1.1.dist-info/METADATA
search_tool-0.1.1.dist-info/WHEEL
search_tool-0.1.1.dist-info/entry_points.txt
search_tool-0.1.1.dist-info/RECORD
